MLeX/__init__.py
MLeX/experiment.py
MLeX/trial.py
mlex_python-0.0.6.dist-info/METADATA
mlex_python-0.0.6.dist-info/WHEEL
mlex_python-0.0.6.dist-info/licenses/LICENSE
mlex_python-0.0.6.dist-info/RECORD
