Metadata-Version: 2.1
Name: mlex-python
Version: 0.0.6
Summary: Lightweight machine learning experiment-tracking tool.
Project-URL: Homepage, https://github.com/phoenixp123/MLeX
Project-URL: Bug Tracker, https://github.com/phoenixp123/MLeX/issues
Author-email: Phoenix Pagan <phoenix.pgn@gmail.com>
License: MIT License
License-File: LICENSE
Classifier: License :: OSI Approved :: MIT License
Classifier: Operating System :: OS Independent
Classifier: Programming Language :: Python :: 3
Requires-Python: >=3.7
Requires-Dist: datetime
Requires-Dist: matplotlib
